version_info/__init__.py
version_info/_version.py
version_info/main.py
git_version_info-0.7.1.dist-info/LICENSE
git_version_info-0.7.1.dist-info/METADATA
git_version_info-0.7.1.dist-info/WHEEL
git_version_info-0.7.1.dist-info/top_level.txt
git_version_info-0.7.1.dist-info/RECORD
